<?xml version="1.0" encoding="UTF-8" standalone="yes"?>
<description>
        <libname>std_sub</libname>
        <functions>
                <function>
                        <name>MatrixSub</name>
                        <output type="MATRIX">
                        </output>
                        <inputs>
                                <input  type="STRING">
                                        <name>topic_name</name>
                                        <desc>Name of the topic to which the function subscribes </desc>
                                </input>
                                <input  type="SCALAR_SCALAR">
                                        <name>size_queue</name>
                                        <desc>Size of the queue</desc>
                                </input>
                                <input  type="SCALAR_SCALAR">
                                        <name>sleep</name>
                                        <desc>sleep duration [-1 : block until receive data ; 0 non-blocking call; N > 0 : sleep during N milliseconds]</desc>
                                </input>
                        </inputs>
                        <icon>ros_input_matrix.svg</icon>
                        <desc>Read MultiArray topic and load values into a Matrix</desc>
                </function>
                <function>
                        <name>ScalarSub</name>
                        <output type="SCALAR">
                        </output>
                        <inputs>
                                <input  type="STRING">
                                        <name>topic_name</name>
                                        <desc>Name of the topic to which the function subscribes </desc>
                                </input>
                                <input  type="SCALAR_SCALAR">
                                        <name>size_queue</name>
                                        <desc>Size of the queue</desc>
                                </input>
                                <input  type="SCALAR_SCALAR">
                                        <name>sleep</name>
                                        <desc>sleep duration [-1 : block until receive data ; 0 non-blocking call; N > 0 : sleep during N milliseconds]</desc>
                                </input>
                        </inputs>
                        <icon>ros_input_scalar.svg</icon>
                        <desc>Read Float64 topic and load values into a Scalar</desc>
		</function>  
	</functions>
</description>

